dancer/__init__.py
dancer/_app.py
dancer/_default_apps.py
dancer/_default_modules.py
dancer/_known_styling.py
dancer/cli.py
dancer/concurrency.py
dancer/config.py
dancer/data.py
dancer/io.py
dancer/py.typed
dancer/qt.py
dancer/qts.py
dancer/security.py
dancer/system.py
dancer/timing.py
dancer/web.py
dancer/_styling/STYLING.md
dancer/_styling/colored_transcription_guide.qst
dancer/_styling/styles/base.qst
dancer/_styling/styles/colored_cherry_blossom.qst
dancer/_styling/styles/colored_evening_sky.qst
dancer/_styling/styles/colored_red_rage.qst
dancer/_styling/styles/colored_summer_sky.qst
dancer/_styling/styles/default_dark.qst
dancer/_styling/styles/default_light.qst
dancer/_styling/styles/high_contrast.qst
dancer/_styling/styles/thick_dark.qst
dancer/_styling/styles/thick_light.qst
dancer/_styling/styles/thin_dark.qst
dancer/_styling/styles/thin_light.qst
dancer/_styling/styles/thin_light_blue.qst
dancer/_styling/styles/thin_light_burgundy.qst
dancer/_styling/styles/thin_light_dark.qst
dancer/_styling/styles/thin_light_green.qst
dancer/_styling/styles/thin_light_purple.qst
dancer/_styling/themes/adalfarus_base.qth
dancer/_styling/themes/adalfarus_chisled.qth
dancer/_styling/themes/adalfarus_default.qth
dancer/_styling/themes/adalfarus_high_contrast.qth
dancer/_styling/themes/adalfarus_modern.qth
dancer/_styling/themes/adalfarus_thick.qth
dancer/_styling/themes/adalfarus_thick_basic.qth
dancer/_styling/themes/adalfarus_thin.qth
dancer/_styling/themes/adalfarus_thin_basic.qth
dncer-0.0.1.0b1.dist-info/licenses/LICENSE
dncer-0.0.1.0b1.dist-info/METADATA
dncer-0.0.1.0b1.dist-info/WHEEL
dncer-0.0.1.0b1.dist-info/top_level.txt
dncer-0.0.1.0b1.dist-info/RECORD
