Metadata-Version: 2.4
Name: dncer
Version: 0.0.1.0b1
Summary: An app framework
Author-email: Cariel Becker <cariel.becker@gmx.de>
Maintainer-email: Cariel Becker <cariel.becker@gmx.de>
License-Expression: LGPL-2.1-or-later
Project-URL: Home, https://pypi.org/project/dancer/
Project-URL: Repository, https://github.com/adalfarus/dancer
Project-URL: Documentation, https://github.com/adalfarus/dancer/wiki
Project-URL: Issue tracker, https://github.com/adalfarus/dancer/issues
Keywords: general,tools,app tools,production,apt
Classifier: Development Status :: 1 - Planning
Classifier: Programming Language :: Python
Classifier: Natural Language :: English
Requires-Python: >=3.10
License-File: LICENSE
Requires-Dist: packaging
Requires-Dist: typing_extensions
Requires-Dist: requests
Requires-Dist: aplustools[all]~=2.0.0.0
Provides-Extra: qt
Requires-Dist: PySide6>=6.7.0; extra == "qt"
Provides-Extra: dev
Requires-Dist: pytest; extra == "dev"
Dynamic: license-file
